sentence_embeddings/__init__.py
sentence_embeddings/embeddings.py
sentence_embeddings-0.0.4.dist-info/METADATA
sentence_embeddings-0.0.4.dist-info/WHEEL
sentence_embeddings-0.0.4.dist-info/top_level.txt
sentence_embeddings-0.0.4.dist-info/RECORD
